github3apps/__init__.py
github3apps/github3apps.py
github3apps.py-0.2.2.dist-info/LICENSE
github3apps.py-0.2.2.dist-info/METADATA
github3apps.py-0.2.2.dist-info/WHEEL
github3apps.py-0.2.2.dist-info/top_level.txt
github3apps.py-0.2.2.dist-info/RECORD
