Metadata-Version: 2.1
Name: github3apps.py
Version: 0.2.2
Summary: Access the Github API as an Application
Home-page: https://github.com/tedivm/github3apps.py
Author: Robert Hafner
Author-email: tedivm@tedivm.com
License: UNKNOWN
Download-URL: https://github.com/tedivm/github3apps.py/archive/v0.2.2.tar.gz
Keywords: automation github apps git
Platform: UNKNOWN
Classifier: Development Status :: 4 - Beta
Classifier: License :: OSI Approved :: MIT License
Classifier: Intended Audience :: Developers
Classifier: Topic :: Software Development :: Version Control
Classifier: Programming Language :: Python :: 3
Requires-Python: >=3
Requires-Dist: cryptography (<3,>=2.1.4)
Requires-Dist: github3.py (<2,>=1)
Requires-Dist: pyjwt (<2,>=1.5.3)
Requires-Dist: requests (<3,>=2.18.0)
Provides-Extra: dev
Requires-Dist: pypandoc ; extra == 'dev'
Requires-Dist: twine ; extra == 'dev'
Requires-Dist: wheel ; extra == 'dev'
